setup.py
fillnull/__init__.py
fillnull/fillnull.py
fillnull.egg-info/PKG-INFO
fillnull.egg-info/SOURCES.txt
fillnull.egg-info/dependency_links.txt
fillnull.egg-info/top_level.txt